sonar_dummy_python_oss/__init__.py
sonar_dummy_python_oss/example.py
sonar_dummy_python_oss-0.1.0.159.dist-info/LICENSE
sonar_dummy_python_oss-0.1.0.159.dist-info/METADATA
sonar_dummy_python_oss-0.1.0.159.dist-info/WHEEL
sonar_dummy_python_oss-0.1.0.159.dist-info/RECORD
