Metadata-Version: 2.1
Name: sonar_dummy_python_oss
Version: 0.1.0.159
Summary: A sample python project used for testing purposes
License: LGPL-3.0-only
Keywords: sonar,sonar-dummy
Author: Jayadeep Kinavoor Madam
Author-email: jayadeep.kinavoormadam@sonarsource.com
Requires-Python: >=3.8
Classifier: Environment :: Console
Classifier: Intended Audience :: Developers
Classifier: License :: OSI Approved :: GNU Lesser General Public License v3 (LGPLv3)
Classifier: Operating System :: OS Independent
Classifier: Programming Language :: Python
Classifier: Programming Language :: Python :: 3
Classifier: Programming Language :: Python :: 3.8
Classifier: Programming Language :: Python :: 3.9
Classifier: Programming Language :: Python :: 3.10
Classifier: Programming Language :: Python :: 3.11
Classifier: Programming Language :: Python :: 3.12
Classifier: Programming Language :: Python :: 3.13
Classifier: Programming Language :: Python :: 3 :: Only
Classifier: Topic :: Software Development :: Quality Assurance
